SimpleVoiceAssistant/SimpleVoiceAssistant.py
SimpleVoiceAssistant/__init__.py
SimpleVoiceAssistant/ollm.py
SimpleVoiceAssistant-1.1.dist-info/METADATA
SimpleVoiceAssistant-1.1.dist-info/WHEEL
SimpleVoiceAssistant-1.1.dist-info/top_level.txt
SimpleVoiceAssistant-1.1.dist-info/RECORD
